LICENSE
MANIFEST.in
README.rst
setup.py
redis_taxon.egg-info/PKG-INFO
redis_taxon.egg-info/SOURCES.txt
redis_taxon.egg-info/dependency_links.txt
redis_taxon.egg-info/top_level.txt
taxon/__init__.py
taxon/core.py
taxon/query.py