Metadata-Version: 1.1
Name: redis-taxon
Version: 0.2.2
Summary: Redis-backed tagged data store
Home-page: https://github.com/jdp/taxon
Author: Justin Poliey
Author-email: justin@getglue.com
License: The MIT License (MIT)
